pythonwin-stubs/__init__.pyi
pythonwin-stubs/dde.pyi
pythonwin-stubs/ntsecuritycon.pyi
pythonwin-stubs/sspicon.pyi
pythonwin-stubs/win32con.pyi
pythonwin-stubs/win32cryptcon.pyi
pythonwin-stubs/win32inetcon.pyi
pythonwin-stubs/win32netcon.pyi
pythonwin-stubs/win32typing.pyi
pythonwin-stubs/win32ui.pyi
pythonwin-stubs/win32uiole.pyi
pythonwin-stubs/winioctlcon.pyi
pywin32_stubs-1.0.7.data/data/Lib/site-packages/pywin32-stubs.pth
win32-stubs/__init__.pyi
win32-stubs/_winxptheme.pyi
win32-stubs/mmapfile.pyi
win32-stubs/odbc.pyi
win32-stubs/perfmon.pyi
win32-stubs/pywintypes.pyi
win32-stubs/servicemanager.pyi
win32-stubs/timer.pyi
win32-stubs/win2kras.pyi
win32-stubs/win32api.pyi
win32-stubs/win32clipboard.pyi
win32-stubs/win32console.pyi
win32-stubs/win32cred.pyi
win32-stubs/win32crypt.pyi
win32-stubs/win32event.pyi
win32-stubs/win32evtlog.pyi
win32-stubs/win32file.pyi
win32-stubs/win32gui.pyi
win32-stubs/win32help.pyi
win32-stubs/win32inet.pyi
win32-stubs/win32job.pyi
win32-stubs/win32lz.pyi
win32-stubs/win32net.pyi
win32-stubs/win32pdh.pyi
win32-stubs/win32pipe.pyi
win32-stubs/win32print.pyi
win32-stubs/win32process.pyi
win32-stubs/win32profile.pyi
win32-stubs/win32ras.pyi
win32-stubs/win32security.pyi
win32-stubs/win32service.pyi
win32-stubs/win32transaction.pyi
win32-stubs/win32ts.pyi
win32-stubs/win32wnet.pyi
win32-stubs/wincerapi.pyi
win32comext-stubs/__init__.pyi
win32comext-stubs/adsi.pyi
win32comext-stubs/axcontrol.pyi
win32comext-stubs/axdebug.pyi
win32comext-stubs/axscript.pyi
win32comext-stubs/directsound.pyi
win32comext-stubs/exchange.pyi
win32comext-stubs/exchdapi.pyi
win32comext-stubs/internet.pyi
win32comext-stubs/mapi.pyi
win32comext-stubs/propsys.pyi
win32comext-stubs/pythoncom.pyi
win32comext-stubs/shell.pyi
win32comext-stubs/win32com.authorization.authorization.pyi
win32helper/__init__.py
win32helper/ntsecuritycon.py
win32helper/sspicon.py
win32helper/win32con.py
win32helper/win32cryptcon.py
win32helper/win32inetcon.py
win32helper/win32netcon.py
pywin32_stubs-1.0.7.dist-info/METADATA
pywin32_stubs-1.0.7.dist-info/WHEEL
pywin32_stubs-1.0.7.dist-info/top_level.txt
pywin32_stubs-1.0.7.dist-info/RECORD
