Metadata-Version: 2.1
Name: pywin32-stubs
Version: 1.0.7
Summary: stubs for pywin32
Home-page: https://pypi.org/project/pywin32-stubs/
Author: Carlos Teng
Author-email: 303359166@qq.com
License: MIT
Keywords: pywin32,stubs
Classifier: Programming Language :: Python
Classifier: Programming Language :: Python :: 3.6
Requires-Dist: pywin32
